i3_find_or_open/main.py
i3_find_or_open-0.6.3.dist-info/LICENSE
i3_find_or_open-0.6.3.dist-info/METADATA
i3_find_or_open-0.6.3.dist-info/WHEEL
i3_find_or_open-0.6.3.dist-info/entry_points.txt
i3_find_or_open-0.6.3.dist-info/RECORD
