Metadata-Version: 2.1
Name: i3_find_or_open
Version: 0.6.3
Summary: A command-line utility that helps you bind keys to find and display a window, or open it if there is no instance running, in i3wm.
License: GPL-3.0-only
Author: Hector Brown
Author-email: hectorjbrown@protonmail.com
Requires-Python: >=3.11,<4.0
Classifier: License :: OSI Approved :: GNU General Public License v3 (GPLv3)
Classifier: Programming Language :: Python :: 3
Classifier: Programming Language :: Python :: 3.11
Classifier: Programming Language :: Python :: 3.12
Requires-Dist: argparse (>=1.4.0,<2.0.0)
Requires-Dist: i3ipc (>=2.2.1,<3.0.0)
